poke_battle_sim/__init__.py
poke_battle_sim/poke_sim.py
poke_battle_sim/conf/__init__.py
poke_battle_sim/conf/global_data.py
poke_battle_sim/conf/global_settings.py
poke_battle_sim/core/__init__.py
poke_battle_sim/core/battle.py
poke_battle_sim/core/battlefield.py
poke_battle_sim/core/move.py
poke_battle_sim/core/pokemon.py
poke_battle_sim/core/trainer.py
poke_battle_sim/data/__init__.py
poke_battle_sim/data/abilities.csv
poke_battle_sim/data/items_gen4.csv
poke_battle_sim/data/move_list.csv
poke_battle_sim/data/natures.csv
poke_battle_sim/data/pokemon_stats.csv
poke_battle_sim/data/type_effectiveness.csv
poke_battle_sim/util/__init__.py
poke_battle_sim/util/process_ability.py
poke_battle_sim/util/process_item.py
poke_battle_sim/util/process_move.py
poke_battle_sim-0.1.6.dist-info/LICENSE
poke_battle_sim-0.1.6.dist-info/METADATA
poke_battle_sim-0.1.6.dist-info/WHEEL
poke_battle_sim-0.1.6.dist-info/top_level.txt
poke_battle_sim-0.1.6.dist-info/zip-safe
poke_battle_sim-0.1.6.dist-info/RECORD
