Metadata-Version: 2.1
Name: poke-battle-sim
Version: 0.1.6
Summary: An open source Python package that provides efficient, customizable simulation of Pokemon battles
Home-page: https://github.com/hiimvincent/poke-battle-sim
Author: Vincent Johnson
Author-email: vincentjohnson1155@gmail.com
License: MIT
Keywords: poke-battle-sim,pokemon,battle simulation,generation iv
Classifier: Programming Language :: Python :: 3
License-File: LICENSE
